cpredict.cpython-312-x86_64-linux-gnu.so
predict.py
pypredict-1.8.0.dist-info/METADATA
pypredict-1.8.0.dist-info/WHEEL
pypredict-1.8.0.dist-info/top_level.txt
pypredict-1.8.0.dist-info/RECORD
pypredict-1.8.0.dist-info/licenses/COPYING
