Metadata-Version: 2.1
Name: pypredict
Version: 1.8.0
Summary: Interface to the Predict satellite tracking and orbital prediction library
Home-page: https://github.com/nsat/pypredict
Author: Jesse Trutna
Author-email: jesse@spire.com
Maintainer: Spire Global Inc
Maintainer-email: opensource@spire.com
Classifier: License :: OSI Approved :: GNU General Public License v2 or later (GPLv2+)
Classifier: Programming Language :: Python :: 2.7
Classifier: Programming Language :: Python :: 3.8
Classifier: Programming Language :: Python :: 3.9
Classifier: Programming Language :: Python :: 3.10
Classifier: Programming Language :: Python :: 3.11
Classifier: Programming Language :: Python :: 3.12
Classifier: Programming Language :: Python :: 3.13
License-File: COPYING
